clusex/__init__.py
clusex/pysex.py
clusex/config/__init__.py
clusex/config/default.conv
clusex/config/default.nnw
clusex/config/default.sex
clusex/config/sex.param
clusex/lib/__init__.py
clusex/lib/cgpng.py
clusex/lib/check.py
clusex/lib/classify_galaxies.py
clusex/lib/ds9.py
clusex/lib/galaxypng.py
clusex/lib/getdesi.py
clusex/lib/init.py
clusex/lib/join.py
clusex/lib/joinfiles.py
clusex/lib/make.py
clusex/lib/maskellipse.py
clusex/lib/radcor.py
clusex/lib/read.py
clusex/lib/satbox.py
clusex/lib/sky.py
clusex/lib/writesex.py
clusex/run/__init__.py
clusex/run/console.py
clusex-2.5.6.dist-info/licenses/LICENSE.txt
clusex-2.5.6.dist-info/METADATA
clusex-2.5.6.dist-info/WHEEL
clusex-2.5.6.dist-info/entry_points.txt
clusex-2.5.6.dist-info/top_level.txt
clusex-2.5.6.dist-info/RECORD
