Metadata-Version: 2.4
Name: CluSex
Version: 2.5.6
Summary: Sextractor on Cluster Galaxies
Home-page: https://github.com/canorve/CluSex
Author: Christopher Añorve, Omar López-Cruz
Author-email: canorve@gmail.com
License: GNU General Public License v3 (GPLv3)
Project-URL: Documentation, https://github.com/canorve/CluSex/blob/master/README.rst
Project-URL: Source, https://github.com/canorve/CluSex
Project-URL: Zenodo, https://doi.org/10.5281/zenodo.7014077
Platform: any
Classifier: Programming Language :: Python
Classifier: Development Status :: 5 - Production/Stable
Classifier: Intended Audience :: Science/Research
Classifier: License :: OSI Approved :: GNU General Public License v3 (GPLv3)
Classifier: Natural Language :: Spanish
Classifier: Natural Language :: English
Classifier: Topic :: Scientific/Engineering :: Astronomy
License-File: LICENSE.txt
Requires-Dist: importlib-metadata; python_version < "3.8"
Requires-Dist: sphinx>=3.2.1
Requires-Dist: numpy>=1.20.3
Requires-Dist: astropy>=4.0.2
Requires-Dist: matplotlib>=3.5.2
Requires-Dist: pandas>=1.3.4
Requires-Dist: Pillow>=8.4.0
Requires-Dist: tk>=0.1.0
Provides-Extra: testing
Requires-Dist: setuptools; extra == "testing"
Requires-Dist: pytest; extra == "testing"
Requires-Dist: pytest-cov; extra == "testing"
Dynamic: license-file
